coleslaw/__init__.py
coleslaw/coleslaw.py
coleslaw_api-0.1.2.dist-info/licenses/LICENSE
coleslaw_api-0.1.2.dist-info/METADATA
coleslaw_api-0.1.2.dist-info/WHEEL
coleslaw_api-0.1.2.dist-info/top_level.txt
coleslaw_api-0.1.2.dist-info/RECORD
