Metadata-Version: 2.4
Name: coleslaw_api
Version: 0.1.2
Summary: Fast Python web server with async MySQL and routing
Home-page: https://github.com/DiscoKnax6808/Coleslaw
Author: Exception2018
Author-email: knax6808real22@gmail.com
Classifier: Programming Language :: Python :: 3
Classifier: License :: OSI Approved :: MIT License
Classifier: Operating System :: OS Independent
Classifier: Framework :: AsyncIO
Requires-Python: >=3.10
License-File: LICENSE
Requires-Dist: aiohttp>=3.8.5
Requires-Dist: aiomysql>=0.1.1
Dynamic: author
Dynamic: author-email
Dynamic: classifier
Dynamic: description
Dynamic: description-content-type
Dynamic: home-page
Dynamic: license-file
Dynamic: requires-dist
Dynamic: requires-python
Dynamic: summary
